colors/__init__.py
colors/ansi.py
colors/constants.py
colors/core.py
colors/hex.py
colors/py.typed
colors/typing.py
colors/utils.py
colors_core-1.1.1.dist-info/LICENSE
colors_core-1.1.1.dist-info/METADATA
colors_core-1.1.1.dist-info/WHEEL
colors_core-1.1.1.dist-info/RECORD
